first_order.py
first_order-0.1.0.dist-info/LICENSE
first_order-0.1.0.dist-info/METADATA
first_order-0.1.0.dist-info/WHEEL
first_order-0.1.0.dist-info/top_level.txt
first_order-0.1.0.dist-info/RECORD
