Metadata-Version: 2.1
Name: first-order
Version: 0.1.0
Summary: Simple first-order logic library
Author-email: Olivia Ryan <olivia.r.dev@gmail.com>
License: MIT License
Project-URL: Issues, https://github.com/olivi-r/first-order/issues
Project-URL: Repository, https://github.com/olivi-r/first-order
License-File: LICENSE
